audio2text/__init__.py
audio2text/audio2text.py
tests/__init__.py
tests/test.py
utils/__init__.py
utils/utils.py
audio2text-1.0.2.dist-info/LICENSE
audio2text-1.0.2.dist-info/METADATA
audio2text-1.0.2.dist-info/WHEEL
audio2text-1.0.2.dist-info/top_level.txt
audio2text-1.0.2.dist-info/RECORD
