Metadata-Version: 2.1
Name: audio2text
Version: 1.0.2
Summary: This package is for extract text from audio/video file
Home-page: https://github.com/LG-1/audio2text
Author: LG
Author-email: ourantech@163.com
License: MIT
Keywords: speech-recognition stt asr english speech-to-text pytorch audio2text
Platform: UNKNOWN
Classifier: Development Status :: 5 - Production/Stable
Classifier: Intended Audience :: Developers
Classifier: License :: OSI Approved :: MIT License
Classifier: Programming Language :: Python :: 3.8
Requires-Dist: torch
Requires-Dist: torchaudio
Provides-Extra: dev
Requires-Dist: check-manifest ; extra == 'dev'
Requires-Dist: sphinx ; extra == 'dev'
Requires-Dist: sphinx-rtd-theme ; extra == 'dev'
Provides-Extra: test
Requires-Dist: coverage ; extra == 'test'
Requires-Dist: nose ; extra == 'test'
